LICENSE
MANIFEST.in
README.rst
setup.py
diffmetrics/__init__.py
diffmetrics/cli.py
diffmetrics/diff.py
diffmetrics.egg-info/PKG-INFO
diffmetrics.egg-info/SOURCES.txt
diffmetrics.egg-info/dependency_links.txt
diffmetrics.egg-info/entry_points.txt
diffmetrics.egg-info/requires.txt
diffmetrics.egg-info/top_level.txt
diffmetrics/metrics/__init__.py
diffmetrics/metrics/flake8.py
diffmetrics/metrics/radon/__init__.py
diffmetrics/metrics/radon/cc.py