Metadata-Version: 1.1
Name: diffmetrics
Version: 1.0
Summary: Diff tool for code metrics
Home-page: https://bitbucket.org/nfinne/diffmetrics
Author: Neal Finne
Author-email: neal@nealfinne.com
License: UNKNOWN
Platform: UNKNOWN
Classifier: Environment :: Console
Classifier: Intended Audience :: Developers
Classifier: License :: OSI Approved :: MIT License
Classifier: Programming Language :: Python
Classifier: Programming Language :: Python :: 2
Classifier: Programming Language :: Python :: 3
Classifier: Topic :: Software Development :: Libraries :: Python Modules
Classifier: Topic :: Software Development :: Quality Assurance
